fabrictestbed_extensions/__init__.py
fabrictestbed_extensions/editors/__init__.py
fabrictestbed_extensions/editors/abc_topology_editor.py
fabrictestbed_extensions/editors/cytoscape_topology_editor.py
fabrictestbed_extensions/editors/geo_topology_editor.py
fabrictestbed_extensions/fablib/__init__.py
fabrictestbed_extensions/fablib/artifact.py
fabrictestbed_extensions/fablib/attestable_switch.py
fabrictestbed_extensions/fablib/component.py
fabrictestbed_extensions/fablib/constants.py
fabrictestbed_extensions/fablib/fablib.py
fabrictestbed_extensions/fablib/facility_port.py
fabrictestbed_extensions/fablib/interface.py
fabrictestbed_extensions/fablib/network_service.py
fabrictestbed_extensions/fablib/node.py
fabrictestbed_extensions/fablib/resources.py
fabrictestbed_extensions/fablib/site.py
fabrictestbed_extensions/fablib/slice.py
fabrictestbed_extensions/fablib/switch.py
fabrictestbed_extensions/fablib/config/__init__.py
fabrictestbed_extensions/fablib/config/config.py
fabrictestbed_extensions/fablib/config/fabric_rc
fabrictestbed_extensions/fablib/config/fabric_rc.yml
fabrictestbed_extensions/images/__init__.py
fabrictestbed_extensions/images/fabric_logo.png
fabrictestbed_extensions/images/server.png
fabrictestbed_extensions/images/slice_rack.png
fabrictestbed_extensions/ui/__init__.py
fabrictestbed_extensions/ui/artifact_manager_ui.py
fabrictestbed_extensions/utils/__init__.py
fabrictestbed_extensions/utils/abc_utils.py
fabrictestbed_extensions/utils/ceph_fs_utils.py
fabrictestbed_extensions/utils/node.py
fabrictestbed_extensions/utils/slice.py
fabrictestbed_extensions/utils/utils.py
fabrictestbed_extensions-1.9.6.dist-info/licenses/LICENSE
fabrictestbed_extensions-1.9.6.dist-info/WHEEL
fabrictestbed_extensions-1.9.6.dist-info/METADATA
fabrictestbed_extensions-1.9.6.dist-info/RECORD
