Metadata-Version: 2.4
Name: fabrictestbed_extensions
Version: 1.9.6
Summary: FABRIC Python Client Library and CLI Extensions
Author-email: Paul Ruth <pruth@renci.org>, Komal Thareja <kthare10@renci.org>
Requires-Python: >=3.9
Classifier: Programming Language :: Python :: 3
Classifier: License :: OSI Approved :: MIT License
Classifier: Operating System :: OS Independent
License-File: LICENSE
Requires-Dist: ipycytoscape
Requires-Dist: ipywidgets
Requires-Dist: ipyleaflet
Requires-Dist: ipycytoscape
Requires-Dist: tabulate
Requires-Dist: fabrictestbed==1.9.0
Requires-Dist: paramiko
Requires-Dist: jinja2>=3.0.0
Requires-Dist: pandas
Requires-Dist: numpy
Requires-Dist: ipython>=8.12.0
Requires-Dist: fabric_fss_utils>=1.6.1
Requires-Dist: recordclass>=0.23.1
Requires-Dist: atomicwrites
Requires-Dist: fabric_paramiko_expect
Requires-Dist: fabric_ceph_client==1.0.2
Requires-Dist: sphinx ; extra == "doc"
Requires-Dist: sphinx-autodoc-typehints ; extra == "doc"
Requires-Dist: furo ; extra == "doc"
Requires-Dist: black==24.* ; extra == "test"
Requires-Dist: isort==5.* ; extra == "test"
Requires-Dist: tox==4.* ; extra == "test"
Requires-Dist: pytest ; extra == "test"
Requires-Dist: coverage[toml] ; extra == "test"
Project-URL: ChangeLog, https://github.com/fabric-testbed/fabrictestbed-extensions/blob/main/CHANGELOG.md
Project-URL: Documentation, https://fabric-fablib.readthedocs.io/
Project-URL: Homepage, https://fabric-testbed.net/
Project-URL: Sources, https://github.com/fabric-testbed/fabrictestbed-extensions
Provides-Extra: doc
Provides-Extra: test
